billobgcfiles/__init__.py
billobgcfiles/__version__.py
billobgcfiles/py.typed
billobgcfiles-0.0.0.dist-info/LICENSE
billobgcfiles-0.0.0.dist-info/WHEEL
billobgcfiles-0.0.0.dist-info/METADATA
billobgcfiles-0.0.0.dist-info/RECORD
