Metadata-Version: 2.1
Name: billobgcfiles
Version: 0.0.0
Summary: internal use
Home-page: https://github.com/billogram
Author: Billogram
Author-email: platform@billogram.com
Requires-Python: >=3.7,<4.0
Classifier: Development Status :: 1 - Planning
Classifier: Programming Language :: Python
Classifier: Programming Language :: Python :: 3
Classifier: Programming Language :: Python :: 3.7
Classifier: Programming Language :: Python :: 3.8
Classifier: Programming Language :: Python :: 3.9
Classifier: Topic :: Software Development
Classifier: Topic :: Software Development :: Libraries
Project-URL: Repository, https://github.com/billogram
